{
    "CQ0432": {
        "icon": "https://images.b728484.com:42666/TCG_GAME_ICONS/CQ9/CQ0432.png",
        "name": "CHICAGOⅡ"
    },
    "CQ0431": {
        "icon": "https://images.b728484.com:42666/TCG_GAME_ICONS/CQ9/CQ0431.png",
        "name": "Xã hội đen"
    },
    "CQ0429": {
        "icon": "https://images.b728484.com:42666/TCG_GAME_ICONS/CQ9/CQ0429.png",
        "name": "Cướp kho báu"
    },
    "CQ0424": {
        "icon": "https://images.b728484.com:42666/TCG_GAME_ICONS/CQ9/CQ0424.png",
        "name": "Bingo sôi nổi"
    },
    "CQ0423": {
        "icon": "https://images.b728484.com:42666/TCG_GAME_ICONS/CQ9/CQ0423.png",
        "name": "Tam quốc anh hùng - Tào Tháo"
    },
    "CQ0422": {
        "icon": "https://images.b728484.com:42666/TCG_GAME_ICONS/CQ9/CQ0422.png",
        "name": "Kho báu của xác ướp"
    },
    "CQ0417": {
        "icon": "https://images.b728484.com:42666/TCG_GAME_ICONS/CQ9/CQ0417.png",
        "name": "Nhà gà"
    },
    "CQ0414": {
        "icon": "https://images.b728484.com:42666/TCG_GAME_ICONS/CQ9/CQ0414.png",
        "name": "Tiền đạo WILD"
    },
    "CQ0413": {
        "icon": "https://images.b728484.com:42666/TCG_GAME_ICONS/CQ9/CQ0413.png",
        "name": "Football Fever M"
    },
    "CQ0412": {
        "icon": "https://images.b728484.com:42666/TCG_GAME_ICONS/CQ9/CQ0412.png",
        "name": "Sốt bóng chày"
    },
    "CQ0411": {
        "icon": "https://images.b728484.com:42666/TCG_GAME_ICONS/CQ9/CQ0411.png",
        "name": "Myeong-ryang"
    },
    "CQ0409": {
        "icon": "https://images.b728484.com:42666/TCG_GAME_ICONS/CQ9/CQ0409.png",
        "name": "Thành phố đêm"
    },
    "CQ0407": {
        "icon": "https://images.b728484.com:42666/TCG_GAME_ICONS/CQ9/CQ0407.png",
        "name": "Gương soi"
    },
    "CQ0406": {
        "icon": "https://images.b728484.com:42666/TCG_GAME_ICONS/CQ9/CQ0406.png",
        "name": "cơn sốt bóng đá"
    },
    "CQ0405": {
        "icon": "https://images.b728484.com:42666/TCG_GAME_ICONS/CQ9/CQ0405.png",
        "name": "888 Cái Thần"
    },
    "CQ0403": {
        "icon": "https://images.b728484.com:42666/TCG_GAME_ICONS/CQ9/CQ0403.png",
        "name": "K.O. hòn đảo"
    },
    "CQ0401": {
        "icon": "https://images.b728484.com:42666/TCG_GAME_ICONS/CQ9/CQ0401.png",
        "name": "Ông Miser"
    },
    "CQ0399": {
        "icon": "https://images.b728484.com:42666/TCG_GAME_ICONS/CQ9/CQ0399.png",
        "name": "Cua Tôm Cá Thái"
    },
    "CQ0398": {
        "icon": "https://images.b728484.com:42666/TCG_GAME_ICONS/CQ9/CQ0398.png",
        "name": "Hổ may mắn"
    },
    "CQ0397": {
        "icon": "https://images.b728484.com:42666/TCG_GAME_ICONS/CQ9/CQ0397.png",
        "name": "Nhào lộn"
    },
    "CQ0395": {
        "icon": "https://images.b728484.com:42666/TCG_GAME_ICONS/CQ9/CQ0395.png",
        "name": "DJ nóng bỏng"
    },
    "CQ0394": {
        "icon": "https://images.b728484.com:42666/TCG_GAME_ICONS/CQ9/CQ0394.png",
        "name": "Rồng Koi"
    },
    "CQ0393": {
        "icon": "https://images.b728484.com:42666/TCG_GAME_ICONS/CQ9/CQ0393.png",
        "name": "Máy quay tiền xu"
    },
    "CQ0392": {
        "icon": "https://images.b728484.com:42666/TCG_GAME_ICONS/CQ9/CQ0392.png",
        "name": "Loy Krathong"
    },
    "CQ0391": {
        "icon": "https://images.b728484.com:42666/TCG_GAME_ICONS/CQ9/CQ0391.png",
        "name": "Chợ nổi"
    },
    "CQ0388": {
        "icon": "https://images.b728484.com:42666/TCG_GAME_ICONS/CQ9/CQ0388.png",
        "name": "Ganesha Jr."
    },
    "CQ0387": {
        "icon": "https://images.b728484.com:42666/TCG_GAME_ICONS/CQ9/CQ0387.png",
        "name": "King Kong Shake"
    },
    "CQ0386": {
        "icon": "https://images.b728484.com:42666/TCG_GAME_ICONS/CQ9/CQ0386.png",
        "name": "Dollar Bomb"
    },
    "CQ0385": {
        "icon": "https://images.b728484.com:42666/TCG_GAME_ICONS/CQ9/CQ0385.png",
        "name": "Trái mạt chược"
    },
    "CQ0384": {
        "icon": "https://images.b728484.com:42666/TCG_GAME_ICONS/CQ9/CQ0384.png",
        "name": "Đèn của Aladdin"
    },
    "CQ0381": {
        "icon": "https://images.b728484.com:42666/TCG_GAME_ICONS/CQ9/CQ0381.png",
        "name": "Kẻ săn quái vật"
    },
    "CQ0380": {
        "icon": "https://images.b728484.com:42666/TCG_GAME_ICONS/CQ9/CQ0380.png",
        "name": "Hanuman Bingo"
    },
    "CQ0379": {
        "icon": "https://images.b728484.com:42666/TCG_GAME_ICONS/CQ9/CQ0379.png",
        "name": "Xoc Dia"
    },
    "CQ0378": {
        "icon": "https://images.b728484.com:42666/TCG_GAME_ICONS/CQ9/CQ0378.png",
        "name": "Vua của Atlantis"
    },
    "CQ0377": {
        "icon": "https://images.b728484.com:42666/TCG_GAME_ICONS/CQ9/CQ0377.png",
        "name": "Dragon Ball Dozer"
    },
    "CQ0376": {
        "icon": "https://images.b728484.com:42666/TCG_GAME_ICONS/CQ9/CQ0376.png",
        "name": "3 2 1 Đi"
    },
    "CQ0375": {
        "icon": "https://images.b728484.com:42666/TCG_GAME_ICONS/CQ9/CQ0375.png",
        "name": "HILO Thái Lan"
    },
    "CQ0374": {
        "icon": "https://images.b728484.com:42666/TCG_GAME_ICONS/CQ9/CQ0374.png",
        "name": "Pinatas nóng"
    },
    "CQ0370": {
        "icon": "https://images.b728484.com:42666/TCG_GAME_ICONS/CQ9/CQ0370.png",
        "name": "Náo động trên thiên đường"
    },
    "CQ0369": {
        "icon": "https://images.b728484.com:42666/TCG_GAME_ICONS/CQ9/CQ0369.png",
        "name": "Da Hong Zhong"
    },
    "CQ0368": {
        "icon": "https://images.b728484.com:42666/TCG_GAME_ICONS/CQ9/CQ0368.png",
        "name": "Da Fa Cai"
    },
    "CQ0367": {
        "icon": "https://images.b728484.com:42666/TCG_GAME_ICONS/CQ9/CQ0367.png",
        "name": "Cò quay mini"
    },
    "CQ0351": {
        "icon": "https://images.b728484.com:42666/TCG_GAME_ICONS/CQ9/CQ0351.png",
        "name": "Oo Ga Cha Ka"
    },
    "CQ0352": {
        "icon": "https://images.b728484.com:42666/TCG_GAME_ICONS/CQ9/CQ0352.png",
        "name": "Đốt cháy bạn"
    },
    "CQ0353": {
        "icon": "https://images.b728484.com:42666/TCG_GAME_ICONS/CQ9/CQ0353.png",
        "name": "Ninja Raccoon"
    },
    "CQ0350": {
        "icon": "https://images.b728484.com:42666/TCG_GAME_ICONS/CQ9/CQ0350.png",
        "name": "rồng rồng rồng"
    },
    "CQ0348": {
        "icon": "https://images.b728484.com:42666/TCG_GAME_ICONS/CQ9/CQ0348.png",
        "name": "Cupids"
    },
    "CQ0343": {
        "icon": "https://images.b728484.com:42666/TCG_GAME_ICONS/CQ9/CQ0343.png",
        "name": "Ngọt Pop"
    },
    "CQ0344": {
        "icon": "https://images.b728484.com:42666/TCG_GAME_ICONS/CQ9/CQ0344.png",
        "name": "Cây Tiền"
    },
    "CQ0338": {
        "icon": "https://images.b728484.com:42666/TCG_GAME_ICONS/CQ9/CQ0338.png",
        "name": "alice run"
    },
    "CQ0336": {
        "icon": "https://images.b728484.com:42666/TCG_GAME_ICONS/CQ9/CQ0336.png",
        "name": "Kho báu của Rồng"
    },
    "CQ0335": {
        "icon": "https://images.b728484.com:42666/TCG_GAME_ICONS/CQ9/CQ0335.png",
        "name": "Trứng gấp mười lần"
    },
    "CQ0327": {
        "icon": "https://images.b728484.com:42666/TCG_GAME_ICONS/CQ9/CQ0327.png",
        "name": "Chúa Ganesha"
    },
    "CQ0324": {
        "icon": "https://images.b728484.com:42666/TCG_GAME_ICONS/CQ9/CQ0324.png",
        "name": "Rồng thần tài"
    },
    "CQ0322": {
        "icon": "https://images.b728484.com:42666/TCG_GAME_ICONS/CQ9/CQ0322.png",
        "name": "Nữ Hoàng Lửa2"
    },
    "CQ0315": {
        "icon": "https://images.b728484.com:42666/TCG_GAME_ICONS/CQ9/CQ0315.png",
        "name": "Ngọc rồng"
    },
    "CQ0314": {
        "icon": "https://images.b728484.com:42666/TCG_GAME_ICONS/CQ9/CQ0314.png",
        "name": "Quả Cầu Thép May Mắn"
    },
    "CQ0311": {
        "icon": "https://images.b728484.com:42666/TCG_GAME_ICONS/CQ9/CQ0311.png",
        "name": "Vịnh Xuân Quyền"
    },
    "CQ0312": {
        "icon": "https://images.b728484.com:42666/TCG_GAME_ICONS/CQ9/CQ0312.png",
        "name": "Sốt dế"
    },
    "CQ0308": {
        "icon": "https://images.b728484.com:42666/TCG_GAME_ICONS/CQ9/CQ0308.png",
        "name": "Sáu Gacha"
    },
    "CQ0300": {
        "icon": "https://images.b728484.com:42666/TCG_GAME_ICONS/CQ9/CQ0300.png",
        "name": "Sói Hoang"
    },
    "CQ0299": {
        "icon": "https://images.b728484.com:42666/TCG_GAME_ICONS/CQ9/CQ0299.png",
        "name": "Thor 2"
    },
    "CQ0296": {
        "icon": "https://images.b728484.com:42666/TCG_GAME_ICONS/CQ9/CQ0296.png",
        "name": "Nhảy Cao 2"
    },
    "CQ0293": {
        "icon": "https://images.b728484.com:42666/TCG_GAME_ICONS/CQ9/CQ0293.png",
        "name": "Gu Gu Gu 3"
    },
    "CQ0292": {
        "icon": "https://images.b728484.com:42666/TCG_GAME_ICONS/CQ9/CQ0292.png",
        "name": "6 Toros"
    },
    "CQ0291": {
        "icon": "https://images.b728484.com:42666/TCG_GAME_ICONS/CQ9/CQ0291.png",
        "name": "Những vị thần Hy Lạp"
    },
    "CQ0284": {
        "icon": "https://images.b728484.com:42666/TCG_GAME_ICONS/CQ9/CQ0284.png",
        "name": "Vàng Của Người Maya"
    },
    "CQ0270": {
        "icon": "https://images.b728484.com:42666/TCG_GAME_ICONS/CQ9/CQ0270.png",
        "name": "Vận May Ma"
    },
    "CQ0001": {
        "icon": "https://images.b728484.com:42666/TCG_GAME_ICONS/CQ9/CQ0001.png",
        "name": "Trái Cây Vua"
    },
    "CQ0002": {
        "icon": "https://images.b728484.com:42666/TCG_GAME_ICONS/CQ9/CQ0002.png",
        "name": "Thần Của Cờ"
    },
    "CQ0003": {
        "icon": "https://images.b728484.com:42666/TCG_GAME_ICONS/CQ9/CQ0003.png",
        "name": "Ma Cà Rồng Nụ Hôn"
    },
    "CQ0004": {
        "icon": "https://images.b728484.com:42666/TCG_GAME_ICONS/CQ9/CQ0004.png",
        "name": "Hoang Dã Người Rừng"
    },
    "CQ0005": {
        "icon": "https://images.b728484.com:42666/TCG_GAME_ICONS/CQ9/CQ0005.png",
        "name": "Ông Giàu"
    },
    "CQ0007": {
        "icon": "https://images.b728484.com:42666/TCG_GAME_ICONS/CQ9/CQ0007.png",
        "name": "Phát Cuồng Nhảy"
    },
    "CQ0008": {
        "icon": "https://images.b728484.com:42666/TCG_GAME_ICONS/CQ9/CQ0008.png",
        "name": "Vì Vậy Ngọt"
    },
    "CQ0009": {
        "icon": "https://images.b728484.com:42666/TCG_GAME_ICONS/CQ9/CQ0009.png",
        "name": "Trung Kui"
    },
    "CQ0010": {
        "icon": "https://images.b728484.com:42666/TCG_GAME_ICONS/CQ9/CQ0010.png",
        "name": "May Mắn Bát"
    },
    "CQ0012": {
        "icon": "https://images.b728484.com:42666/TCG_GAME_ICONS/CQ9/CQ0012.png",
        "name": "Kho Báu Nhà"
    },
    "CQ0013": {
        "icon": "https://images.b728484.com:42666/TCG_GAME_ICONS/CQ9/CQ0013.png",
        "name": "Sakura Truyền Thuyết"
    },
    "CQ0015": {
        "icon": "https://images.b728484.com:42666/TCG_GAME_ICONS/CQ9/CQ0015.png",
        "name": "Gu Gu Gu"
    },
    "CQ0016": {
        "icon": "https://images.b728484.com:42666/TCG_GAME_ICONS/CQ9/CQ0016.png",
        "name": "Siêu 5"
    },
    "CQ0017": {
        "icon": "https://images.b728484.com:42666/TCG_GAME_ICONS/CQ9/CQ0017.png",
        "name": "Sư Tử Lớn"
    },
    "CQ0019": {
        "icon": "https://images.b728484.com:42666/TCG_GAME_ICONS/CQ9/CQ0019.png",
        "name": "Spin Nóng"
    },
    "CQ0020": {
        "icon": "https://images.b728484.com:42666/TCG_GAME_ICONS/CQ9/CQ0020.png",
        "name": "888"
    },
    "CQ0021": {
        "icon": "https://images.b728484.com:42666/TCG_GAME_ICONS/CQ9/CQ0021.png",
        "name": "Truyền Thuyết Về Sói"
    },
    "CQ0022": {
        "icon": "https://images.b728484.com:42666/TCG_GAME_ICONS/CQ9/CQ0022.png",
        "name": "Khỉ Văn Phòng Truyền Thuyết"
    },
    "CQ0023": {
        "icon": "https://images.b728484.com:42666/TCG_GAME_ICONS/CQ9/CQ0023.png",
        "name": "Nguyên Bảo"
    },
    "CQ0024": {
        "icon": "https://images.b728484.com:42666/TCG_GAME_ICONS/CQ9/CQ0024.png",
        "name": "Phát Cuồng Nhảy2"
    },
    "CQ0026": {
        "icon": "https://images.b728484.com:42666/TCG_GAME_ICONS/CQ9/CQ0026.png",
        "name": "777"
    },
    "CQ0027": {
        "icon": "https://images.b728484.com:42666/TCG_GAME_ICONS/CQ9/CQ0027.png",
        "name": "Thê Giơi Phep ThuậT"
    },
    "CQ0029": {
        "icon": "https://images.b728484.com:42666/TCG_GAME_ICONS/CQ9/CQ0029.png",
        "name": "Thế Giới Nước"
    },
    "CQ0031": {
        "icon": "https://images.b728484.com:42666/TCG_GAME_ICONS/CQ9/CQ0031.png",
        "name": "Thần Chiến Tranh"
    },
    "CQ0032": {
        "icon": "https://images.b728484.com:42666/TCG_GAME_ICONS/CQ9/CQ0032.png",
        "name": "Thám Tử Dee"
    },
    "CQ0033": {
        "icon": "https://images.b728484.com:42666/TCG_GAME_ICONS/CQ9/CQ0033.png",
        "name": "Đốt Tàu"
    },
    "CQ0034": {
        "icon": "https://images.b728484.com:42666/TCG_GAME_ICONS/CQ9/CQ0034.png",
        "name": "Gophers Chiến"
    },
    "CQ0035": {
        "icon": "https://images.b728484.com:42666/TCG_GAME_ICONS/CQ9/CQ0035.png",
        "name": "Tất Cả Hoang Dã"
    },
    "CQ0036": {
        "icon": "https://images.b728484.com:42666/TCG_GAME_ICONS/CQ9/CQ0036.png",
        "name": "Apsaras"
    },
    "CQ0039": {
        "icon": "https://images.b728484.com:42666/TCG_GAME_ICONS/CQ9/CQ0039.png",
        "name": "Sherlock Holmes"
    },
    "CQ0041": {
        "icon": "https://images.b728484.com:42666/TCG_GAME_ICONS/CQ9/CQ0041.png",
        "name": "Trái Cây Vua Sang Trọng"
    },
    "CQ0043": {
        "icon": "https://images.b728484.com:42666/TCG_GAME_ICONS/CQ9/CQ0043.png",
        "name": "Sói Trăng"
    },
    "CQ0044": {
        "icon": "https://images.b728484.com:42666/TCG_GAME_ICONS/CQ9/CQ0044.png",
        "name": "Pharaoh Vàng"
    },
    "CQ0046": {
        "icon": "https://images.b728484.com:42666/TCG_GAME_ICONS/CQ9/CQ0046.png",
        "name": "Hành Tinh Cô Đơn"
    },
    "CQ0047": {
        "icon": "https://images.b728484.com:42666/TCG_GAME_ICONS/CQ9/CQ0047.png",
        "name": "Tốt Vận May"
    },
    "CQ0048": {
        "icon": "https://images.b728484.com:42666/TCG_GAME_ICONS/CQ9/CQ0048.png",
        "name": "Ngây Ngất Xiếc"
    },
    "CQ0049": {
        "icon": "https://images.b728484.com:42666/TCG_GAME_ICONS/CQ9/CQ0049.png",
        "name": "Nhảy Cao"
    },
    "CQ0052": {
        "icon": "https://images.b728484.com:42666/TCG_GAME_ICONS/CQ9/CQ0052.png",
        "name": "Cơn Thịnh Nộ Của Sự Giàu Có"
    },
    "CQ0096": {
        "icon": "https://images.b728484.com:42666/TCG_GAME_ICONS/CQ9/CQ0096.png",
        "name": "Gu Gu Gu 2"
    },
    "CQ0097": {
        "icon": "https://images.b728484.com:42666/TCG_GAME_ICONS/CQ9/CQ0097.png",
        "name": "55 Rồng Tim"
    },
    "CQ0100": {
        "icon": "https://images.b728484.com:42666/TCG_GAME_ICONS/CQ9/CQ0100.png",
        "name": "Hài Hước Alpica"
    },
    "CQ0101": {
        "icon": "https://images.b728484.com:42666/TCG_GAME_ICONS/CQ9/CQ0101.png",
        "name": "Ảnh Nóng"
    },
    "CQ0102": {
        "icon": "https://images.b728484.com:42666/TCG_GAME_ICONS/CQ9/CQ0102.png",
        "name": "Wan Bảo Dino"
    },
    "CQ0104": {
        "icon": "https://images.b728484.com:42666/TCG_GAME_ICONS/CQ9/CQ0104.png",
        "name": "Trứng Vàng"
    },
    "CQ0105": {
        "icon": "https://images.b728484.com:42666/TCG_GAME_ICONS/CQ9/CQ0105.png",
        "name": "Thần May Mắn"
    },
    "CQ0106": {
        "icon": "https://images.b728484.com:42666/TCG_GAME_ICONS/CQ9/CQ0106.png",
        "name": "WonWonWon"
    },
    "CQ0109": {
        "icon": "https://images.b728484.com:42666/TCG_GAME_ICONS/CQ9/CQ0109.png",
        "name": "Tiếng Nuozha"
    },
    "CQ0110": {
        "icon": "https://images.b728484.com:42666/TCG_GAME_ICONS/CQ9/CQ0110.png",
        "name": "Goku Ăn Cắp Trái Đào"
    },
    "CQ0111": {
        "icon": "https://images.b728484.com:42666/TCG_GAME_ICONS/CQ9/CQ0111.png",
        "name": "Chúc May Mắn Hàng Năm"
    },
    "CQ0112": {
        "icon": "https://images.b728484.com:42666/TCG_GAME_ICONS/CQ9/CQ0112.png",
        "name": "Cornucopia"
    },
    "CQ0113": {
        "icon": "https://images.b728484.com:42666/TCG_GAME_ICONS/CQ9/CQ0113.png",
        "name": "Phượng Hoàng Đỏ"
    },
    "CQ0114": {
        "icon": "https://images.b728484.com:42666/TCG_GAME_ICONS/CQ9/CQ0114.png",
        "name": "Apollo"
    },
    "CQ0115": {
        "icon": "https://images.b728484.com:42666/TCG_GAME_ICONS/CQ9/CQ0115.png",
        "name": "Poseidon"
    },
    "CQ0117": {
        "icon": "https://images.b728484.com:42666/TCG_GAME_ICONS/CQ9/CQ0117.png",
        "name": "Đảo Châu Báu"
    },
    "CQ0119": {
        "icon": "https://images.b728484.com:42666/TCG_GAME_ICONS/CQ9/CQ0119.png",
        "name": "Tâm Trạng Mùa Hè"
    },
    "CQ0120": {
        "icon": "https://images.b728484.com:42666/TCG_GAME_ICONS/CQ9/CQ0120.png",
        "name": "Thần Zeus"
    },
    "CQ0121": {
        "icon": "https://images.b728484.com:42666/TCG_GAME_ICONS/CQ9/CQ0121.png",
        "name": "Cuộc Chiến Quái Thú"
    },
    "CQ0123": {
        "icon": "https://images.b728484.com:42666/TCG_GAME_ICONS/CQ9/CQ0123.png",
        "name": "Cháy Nữ Hoàng"
    },
    "CQ0125": {
        "icon": "https://images.b728484.com:42666/TCG_GAME_ICONS/CQ9/CQ0125.png",
        "name": "Con Tắc Kè"
    },
    "CQ0127": {
        "icon": "https://images.b728484.com:42666/TCG_GAME_ICONS/CQ9/CQ0127.png",
        "name": "Cúp Thế Giới Nga"
    },
    "CQ0130": {
        "icon": "https://images.b728484.com:42666/TCG_GAME_ICONS/CQ9/CQ0130.png",
        "name": "Giày Bóng Đá"
    },
    "CQ0131": {
        "icon": "https://images.b728484.com:42666/TCG_GAME_ICONS/CQ9/CQ0131.png",
        "name": "Bóng Đá Bé"
    },
    "CQ0133": {
        "icon": "https://images.b728484.com:42666/TCG_GAME_ICONS/CQ9/CQ0133.png",
        "name": "Đội Bóng Siêu Sao"
    },
    "CQ0135": {
        "icon": "https://images.b728484.com:42666/TCG_GAME_ICONS/CQ9/CQ0135.png",
        "name": "Muay Thái"
    },
    "CQ0136": {
        "icon": "https://images.b728484.com:42666/TCG_GAME_ICONS/CQ9/CQ0136.png",
        "name": "Vũ Công Quyến Rũ"
    },
    "CQ0137": {
        "icon": "https://images.b728484.com:42666/TCG_GAME_ICONS/CQ9/CQ0137.png",
        "name": "Phát Cuồng Cao"
    },
    "CQ0138": {
        "icon": "https://images.b728484.com:42666/TCG_GAME_ICONS/CQ9/CQ0138.png",
        "name": "May Mắn Hộp"
    },
    "CQ0139": {
        "icon": "https://images.b728484.com:42666/TCG_GAME_ICONS/CQ9/CQ0139.png",
        "name": "Sàn Nhảy Đêm"
    },
    "CQ0140": {
        "icon": "https://images.b728484.com:42666/TCG_GAME_ICONS/CQ9/CQ0140.png",
        "name": "Chạy Toro"
    },
    "CQ0153": {
        "icon": "https://images.b728484.com:42666/TCG_GAME_ICONS/CQ9/CQ0153.png",
        "name": "Thần Sấm"
    },
    "CQ0154": {
        "icon": "https://images.b728484.com:42666/TCG_GAME_ICONS/CQ9/CQ0154.png",
        "name": "NhảY Cao Hơn"
    },
    "CQ0155": {
        "icon": "https://images.b728484.com:42666/TCG_GAME_ICONS/CQ9/CQ0155.png",
        "name": "Điện Thoại Di Động"
    },
    "CQ0161": {
        "icon": "https://images.b728484.com:42666/TCG_GAME_ICONS/CQ9/CQ0161.png",
        "name": "Trái Cây Lễ Hội Hóa Trang"
    },
    "CQ0162": {
        "icon": "https://images.b728484.com:42666/TCG_GAME_ICONS/CQ9/CQ0162.png",
        "name": "Viên Ngọc Sang Trọng"
    },
    "CQ0163": {
        "icon": "https://images.b728484.com:42666/TCG_GAME_ICONS/CQ9/CQ0163.png",
        "name": "Charm Parm Parm"
    },
    "CQ0165": {
        "icon": "https://images.b728484.com:42666/TCG_GAME_ICONS/CQ9/CQ0165.png",
        "name": "Điện Thoại Di Động Nhảy Cao Hơn"
    },
    "CQ0166": {
        "icon": "https://images.b728484.com:42666/TCG_GAME_ICONS/CQ9/CQ0166.png",
        "name": "Phát Cuồng Nhảy Di Động"
    },
    "CQ0170": {
        "icon": "https://images.b728484.com:42666/TCG_GAME_ICONS/CQ9/CQ0170.png",
        "name": "Thám Tử Dee 2"
    },
    "CQ0173": {
        "icon": "https://images.b728484.com:42666/TCG_GAME_ICONS/CQ9/CQ0173.png",
        "name": "Bay Ra Khỏi"
    },
    "CQ0174": {
        "icon": "https://images.b728484.com:42666/TCG_GAME_ICONS/CQ9/CQ0174.png",
        "name": "Mr Bean"
    },
    "CQ0175": {
        "icon": "https://images.b728484.com:42666/TCG_GAME_ICONS/CQ9/CQ0175.png",
        "name": "Rừng Nhiệt Đới Đảng"
    },
    "CQ0178": {
        "icon": "https://images.b728484.com:42666/TCG_GAME_ICONS/CQ9/CQ0178.png",
        "name": "Hollywood Có Thú Nuôi"
    },
    "CQ0179": {
        "icon": "https://images.b728484.com:42666/TCG_GAME_ICONS/CQ9/CQ0179.png",
        "name": "May Mắn 3"
    },
    "CQ0180": {
        "icon": "https://images.b728484.com:42666/TCG_GAME_ICONS/CQ9/CQ0180.png",
        "name": "Kho Báu Của Seti"
    },
    "CQ0181": {
        "icon": "https://images.b728484.com:42666/TCG_GAME_ICONS/CQ9/CQ0181.png",
        "name": "Hoang Dã Tin Giờ Chót"
    },
    "CQ0182": {
        "icon": "https://images.b728484.com:42666/TCG_GAME_ICONS/CQ9/CQ0182.png",
        "name": "Nữ Hoàng Chết"
    },
    "CQ0183": {
        "icon": "https://images.b728484.com:42666/TCG_GAME_ICONS/CQ9/CQ0183.png",
        "name": "Giáng Sinh"
    },
    "CQ0185": {
        "icon": "https://images.b728484.com:42666/TCG_GAME_ICONS/CQ9/CQ0185.png",
        "name": "Phát Cuồng Nhảy 2 M"
    },
    "CQ0186": {
        "icon": "https://images.b728484.com:42666/TCG_GAME_ICONS/CQ9/CQ0186.png",
        "name": "Dơi May Mắn M"
    },
    "CQ0187": {
        "icon": "https://images.b728484.com:42666/TCG_GAME_ICONS/CQ9/CQ0187.png",
        "name": "Zeus M"
    },
    "CQ0188": {
        "icon": "https://images.b728484.com:42666/TCG_GAME_ICONS/CQ9/CQ0188.png",
        "name": "Sàn Nhảy Đêm M"
    },
    "CQ0189": {
        "icon": "https://images.b728484.com:42666/TCG_GAME_ICONS/CQ9/CQ0189.png",
        "name": "Hỏa Chibi M"
    },
    "CQ0190": {
        "icon": "https://images.b728484.com:42666/TCG_GAME_ICONS/CQ9/CQ0190.png",
        "name": "Câu Chuyện Xmas"
    },
    "CQ0191": {
        "icon": "https://images.b728484.com:42666/TCG_GAME_ICONS/CQ9/CQ0191.png",
        "name": "Thần Của Binh Binh M"
    },
    "CQ0192": {
        "icon": "https://images.b728484.com:42666/TCG_GAME_ICONS/CQ9/CQ0192.png",
        "name": "Gu Gu Gu 2 M"
    },
    "CQ0193": {
        "icon": "https://images.b728484.com:42666/TCG_GAME_ICONS/CQ9/CQ0193.png",
        "name": "Pháp Cai Thần M"
    },
    "CQ0194": {
        "icon": "https://images.b728484.com:42666/TCG_GAME_ICONS/CQ9/CQ0194.png",
        "name": "Tốt Tạp Chí Vận May M"
    },
    "CQ0195": {
        "icon": "https://images.b728484.com:42666/TCG_GAME_ICONS/CQ9/CQ0195.png",
        "name": "Gu Gu Gu M"
    },
    "CQ0206": {
        "icon": "https://images.b728484.com:42666/TCG_GAME_ICONS/CQ9/CQ0206.png",
        "name": "Vịnh Cai Thần"
    },
    "CQ0207": {
        "icon": "https://images.b728484.com:42666/TCG_GAME_ICONS/CQ9/CQ0207.png",
        "name": "Xứ Sở Thần Tiên"
    },
    "CQ0208": {
        "icon": "https://images.b728484.com:42666/TCG_GAME_ICONS/CQ9/CQ0208.png",
        "name": "Skr Skr"
    },
    "CQ0209": {
        "icon": "https://images.b728484.com:42666/TCG_GAME_ICONS/CQ9/CQ0209.png",
        "name": "Zuma Hoang Dã"
    },
    "CQ0215": {
        "icon": "https://images.b728484.com:42666/TCG_GAME_ICONS/CQ9/CQ0215.png",
        "name": "Kim Tự Tháp Đột Kích"
    },
    "CQ0216": {
        "icon": "https://images.b728484.com:42666/TCG_GAME_ICONS/CQ9/CQ0216.png",
        "name": "Voi Bất Khả Chiến Bại"
    },
    "CQ0217": {
        "icon": "https://images.b728484.com:42666/TCG_GAME_ICONS/CQ9/CQ0217.png",
        "name": "Nữ Hoàng Tuyết"
    },
    "CQ0218": {
        "icon": "https://images.b728484.com:42666/TCG_GAME_ICONS/CQ9/CQ0218.png",
        "name": "5 Đức Chúa Trời Quái Thú"
    },
    "CQ0223": {
        "icon": "https://images.b728484.com:42666/TCG_GAME_ICONS/CQ9/CQ0223.png",
        "name": "Bánh Xe Tiền"
    },
    "CQ0224": {
        "icon": "https://images.b728484.com:42666/TCG_GAME_ICONS/CQ9/CQ0224.png",
        "name": "Kẻ Đánh Cắp Vàng"
    },
    "CQ0225": {
        "icon": "https://images.b728484.com:42666/TCG_GAME_ICONS/CQ9/CQ0225.png",
        "name": "Hỏa Chibi 2"
    },
    "CQ0229": {
        "icon": "https://images.b728484.com:42666/TCG_GAME_ICONS/CQ9/CQ0229.png",
        "name": "Meow Khác"
    },
    "CQ0230": {
        "icon": "https://images.b728484.com:42666/TCG_GAME_ICONS/CQ9/CQ0230.png",
        "name": "Chạy Động Vật"
    },
    "CQ0231": {
        "icon": "https://images.b728484.com:42666/TCG_GAME_ICONS/CQ9/CQ0231.png",
        "name": "Lợn May Mắn"
    },
    "CQ0234": {
        "icon": "https://images.b728484.com:42666/TCG_GAME_ICONS/CQ9/CQ0234.png",
        "name": "Hephaestus"
    },
    "CQ0235": {
        "icon": "https://images.b728484.com:42666/TCG_GAME_ICONS/CQ9/CQ0235.png",
        "name": "Pháp Cai Fu Wa"
    },
    "CQ0237": {
        "icon": "https://images.b728484.com:42666/TCG_GAME_ICONS/CQ9/CQ0237.png",
        "name": "5 Quyền Anh"
    },
    "CQ0238": {
        "icon": "https://images.b728484.com:42666/TCG_GAME_ICONS/CQ9/CQ0238.png",
        "name": "Kho Tàng Kim Cương"
    },
    "CQ0239": {
        "icon": "https://images.b728484.com:42666/TCG_GAME_ICONS/CQ9/CQ0239.png",
        "name": "Thợ Săn Rồng"
    },
    "CQ0240": {
        "icon": "https://images.b728484.com:42666/TCG_GAME_ICONS/CQ9/CQ0240.png",
        "name": "Đèn Trời"
    },
    "CQ0241": {
        "icon": "https://images.b728484.com:42666/TCG_GAME_ICONS/CQ9/CQ0241.png",
        "name": "Chùm Hoa"
    },
    "CQ0244": {
        "icon": "https://images.b728484.com:42666/TCG_GAME_ICONS/CQ9/CQ0244.png",
        "name": "Tạp Chí Vận May Totem"
    },
    "CQ0245": {
        "icon": "https://images.b728484.com:42666/TCG_GAME_ICONS/CQ9/CQ0245.png",
        "name": "Sáu Kẹo"
    },
    "CQ0247": {
        "icon": "https://images.b728484.com:42666/TCG_GAME_ICONS/CQ9/CQ0247.png",
        "name": "Di Chuyển N Nhảy"
    },
    "CQ0250": {
        "icon": "https://images.b728484.com:42666/TCG_GAME_ICONS/CQ9/CQ0250.png",
        "name": "Giày Cao Cổ"
    },
    "CQ0251": {
        "icon": "https://images.b728484.com:42666/TCG_GAME_ICONS/CQ9/CQ0251.png",
        "name": "Shou-Xin"
    },
    "CQ0253": {
        "icon": "https://images.b728484.com:42666/TCG_GAME_ICONS/CQ9/CQ0253.png",
        "name": "Đôi Bay"
    },
    "CQ0260": {
        "icon": "https://images.b728484.com:42666/TCG_GAME_ICONS/CQ9/CQ0260.png",
        "name": "Kronos"
    },
    "CQ0261": {
        "icon": "https://images.b728484.com:42666/TCG_GAME_ICONS/CQ9/CQ0261.png",
        "name": "Cirque De Fous"
    },
    "CQ0262": {
        "icon": "https://images.b728484.com:42666/TCG_GAME_ICONS/CQ9/CQ0262.png",
        "name": "Pháp Cao Thần 2"
    },
    "CQ0266": {
        "icon": "https://images.b728484.com:42666/TCG_GAME_ICONS/CQ9/CQ0266.png",
        "name": "Mùa Vọng"
    },
    "CQ0267": {
        "icon": "https://images.b728484.com:42666/TCG_GAME_ICONS/CQ9/CQ0267.png",
        "name": "Herials"
    }
}